sfparticles/__init__.py
sfparticles/cpu.py
sfparticles/fields.py
sfparticles/gpu.py
sfparticles/inline.py
sfparticles/particles.py
sfparticles/simulation.py
sfparticles/qed/__init__.py
sfparticles/qed/optical_depth.py
sfparticles/qed/optical_depth_tables.h5
sfparticles/qed/optical_depth_tables.py
sfparticles/qed/rejection_sampling.py
sfparticles/qed/rejection_sampling_tables.h5
sfparticles/qed/rejection_sampling_tables.py
sfparticles-0.4.12.dist-info/licenses/LICENSE
sfparticles-0.4.12.dist-info/METADATA
sfparticles-0.4.12.dist-info/WHEEL
sfparticles-0.4.12.dist-info/top_level.txt
sfparticles-0.4.12.dist-info/RECORD
