Metadata-Version: 2.4
Name: sfparticles
Version: 0.4.12
Summary: Simulation toolkit for particle tracking in strong fields.
Author-email: xsgeng <xsgeng@siom.ac.cn>
License:                     GNU GENERAL PUBLIC LICENSE
Project-URL: Homepage, https://github.com/xsgeng/sfparticles
Keywords: Plasma Physics,Strong field
Classifier: Development Status :: 3 - Alpha
Classifier: Intended Audience :: Science/Research
Classifier: Programming Language :: Python :: 3.9
Requires-Python: >=3.9
License-File: LICENSE
Requires-Dist: numpy
Requires-Dist: numba
Requires-Dist: scipy
Requires-Dist: h5py
Requires-Dist: tqdm
Dynamic: license-file
